fluxgapfill/__init__.py
fluxgapfill/__version__.py
fluxgapfill/main.py
fluxgapfill/gapfill/__init__.py
fluxgapfill/gapfill/gapfill.py
fluxgapfill/metrics/__init__.py
fluxgapfill/metrics/metrics.py
fluxgapfill/models/__init__.py
fluxgapfill/models/base.py
fluxgapfill/models/ensemble.py
fluxgapfill/models/models.py
fluxgapfill/predictors/__init__.py
fluxgapfill/predictors/check.py
fluxgapfill/predictors/parse.py
fluxgapfill/predictors/process.py
fluxgapfill/preprocess/__init__.py
fluxgapfill/preprocess/artificial.py
fluxgapfill/preprocess/distances.py
fluxgapfill/preprocess/load.py
fluxgapfill/preprocess/preprocess.py
fluxgapfill/test/__init__.py
fluxgapfill/test/test.py
fluxgapfill/train/__init__.py
fluxgapfill/train/train.py
methane-gapfill-ml/__init__.py
methane-gapfill-ml/__version__.py
methane-gapfill-ml/main.py
methane-gapfill-ml/gapfill/__init__.py
methane-gapfill-ml/gapfill/gapfill.py
methane-gapfill-ml/metrics/__init__.py
methane-gapfill-ml/metrics/metrics.py
methane-gapfill-ml/models/__init__.py
methane-gapfill-ml/models/base.py
methane-gapfill-ml/models/ensemble.py
methane-gapfill-ml/models/models.py
methane-gapfill-ml/predictors/__init__.py
methane-gapfill-ml/predictors/check.py
methane-gapfill-ml/predictors/parse.py
methane-gapfill-ml/predictors/process.py
methane-gapfill-ml/preprocess/__init__.py
methane-gapfill-ml/preprocess/artificial.py
methane-gapfill-ml/preprocess/distances.py
methane-gapfill-ml/preprocess/load.py
methane-gapfill-ml/preprocess/preprocess.py
methane-gapfill-ml/test/__init__.py
methane-gapfill-ml/test/test.py
methane-gapfill-ml/train/__init__.py
methane-gapfill-ml/train/train.py
fluxgapfill-0.1.0.dist-info/LICENSE
fluxgapfill-0.1.0.dist-info/METADATA
fluxgapfill-0.1.0.dist-info/WHEEL
fluxgapfill-0.1.0.dist-info/top_level.txt
fluxgapfill-0.1.0.dist-info/RECORD
