Metadata-Version: 2.1
Name: fluxgapfill
Version: 0.1.0
Summary: A package for machine learning driven methane gapfilling.
Home-page: https://github.com/stanfordmlgroup/methane-gapfill-mlt
Author: Jeremy Irvin & Yulun Zhou
Author-email: yulunmail@gmail.com
License: MIT
Platform: UNKNOWN
Classifier: License :: OSI Approved :: MIT License
Classifier: Programming Language :: Python
Classifier: Programming Language :: Python :: 3
Classifier: Programming Language :: Python :: 3.6
Classifier: Programming Language :: Python :: Implementation :: CPython
Classifier: Programming Language :: Python :: Implementation :: PyPy
Requires-Python: >=3.6.0
Requires-Dist: pandas
Requires-Dist: scipy
Requires-Dist: scikit-learn
Requires-Dist: fire
Requires-Dist: ngboost
Requires-Dist: tqdm
Requires-Dist: xgboost
